{
  "meta": {
    "tags": [
      "image",
      "picture",
      "figure",
      "icons",
      "data",
      "information",
      "happening"
    ]
  },
  "event": {
    "heading": "Lorem ipsum dolor et",
    "stateText": "Dolor sit amet"
  },
  "figure": {
    "caption": "Img: Avaena idor",
    "img": {
      "alt": "Lorem ipsum",
      "defaultUrl": "https://picsum.photos/960/740/?random"
    }
  },
  "infoList": {
    "icons": {
      "entries": [
        {
          "modifiers": "osg-u-icon-calendar",
          "srText": "Calendar",
          "text": "Praesent 22. sed",
          "subtext": "kl.17:22",
          "linkText": "Vestibulum varius nisi",
          "link": "#"
        },
        {
          "modifiers": "osg-u-icon-location-pin",
          "srText": "Location",
          "text": "Fringilla Mattis Tortor",
          "linkText": "Aliquam erat volutpat",
          "link": "#"
        }
      ]
    }
  }
}
